README.md
setup.py
indies/__init__.py
indies.egg-info/PKG-INFO
indies.egg-info/SOURCES.txt
indies.egg-info/dependency_links.txt
indies.egg-info/not-zip-safe
indies.egg-info/requires.txt
indies.egg-info/top_level.txt