Metadata-Version: 1.0
Name: indies
Version: 0.1.1
Summary: Financial Indicators Library
Home-page: https://github.com/miti0/indies
Author: Miro Karpis
Author-email: miroslav.karpis@gmail.com
License: Apache License 2.0
Platform: UNKNOWN
